axolotl/__init__.py
axolotl/__main__.py
axolotl/utils.py
axolotl/backup_and_restore/__init__.py
axolotl/backup_and_restore/backup_and_restore.py
axolotl/backup_and_restore/client.py
axolotl/db_utils/__init__.py
axolotl/db_utils/db_utils.py
axolotl/db_utils/move.py
axolotl_dbu-0.1.2.dist-info/METADATA
axolotl_dbu-0.1.2.dist-info/WHEEL
axolotl_dbu-0.1.2.dist-info/entry_points.txt
axolotl_dbu-0.1.2.dist-info/top_level.txt
axolotl_dbu-0.1.2.dist-info/RECORD
