Metadata-Version: 2.1
Name: axolotl-dbu
Version: 0.1.2
Summary: Teia Labs DB Utils packege
Home-page: https://github.com/TeiaLabs/axolotl
Author: TeiaLabs
Author-email: contato@teialabs.com
Requires-Python: >=3.11
Requires-Dist: rich
Requires-Dist: typer
Requires-Dist: python-dotenv
Requires-Dist: pymongo
Requires-Dist: pymilvus
Requires-Dist: numpy
Requires-Dist: PyYAML
Provides-Extra: test
Requires-Dist: pytest ; extra == 'test'
Requires-Dist: pytest-cov ; extra == 'test'
Requires-Dist: redb-odm ; extra == 'test'
